{
    "args":{
        "aa":"rand-m9-mstd0.5-inc1",
        "apex_amp":false,
        "apex_amp_loss_scale":null,
        "batch_size":128,
        "bce_loss":false,
        "bce_target_thresh":null,
        "canvas_bmm_pct":0.5,
        "canvas_kernel":"",
        "canvas_load_checkpoint":"",
        "canvas_log_dir":"/data/zhaocg/canvas_imagenet_no_ckp_5_epoch_logs/",
        "canvas_max_macs":0,
        "canvas_max_params":0,
        "canvas_min_macs":0,
        "canvas_min_params":0,
        "canvas_min_proxy_kernel_scale":0.2,
        "canvas_oss_bucket":"ep5_no_ckp",
        "canvas_proxy_kernel_scale_limit":0.3,
        "canvas_proxy_root":"",
        "canvas_proxy_threshold":70.0,
        "canvas_rounds":0,
        "canvas_seed":"pure",
        "canvas_selector_address":"http://43.138.119.173:8000",
        "checkpoint_hist":10,
        "clip_grad":null,
        "clip_mode":"norm",
        "color_jitter":0.4,
        "cooldown_epochs":0,
        "crop_pct":0.9,
        "cutmix":1.0,
        "cutmix_minmax":null,
        "decay_epochs":0.0,
        "decay_rate":0.1,
        "device":"cuda:0",
        "dist_bn":"reduce",
        "distributed":false,
        "drop":0.0,
        "drop_block":null,
        "drop_path":null,
        "epochs":5,
        "eval_metric":"top1",
        "forbid_eval_nan":false,
        "gp":null,
        "hflip":0.5,
        "img_size":null,
        "input_size":[
            3,
            224,
            224
        ],
        "interpolation":"bicubic",
        "jsd_loss":false,
        "local_rank":0,
        "log_interval":100,
        "lr":0.001,
        "lr_cycle_decay":0.5,
        "lr_cycle_limit":1,
        "lr_cycle_mul":1.0,
        "lr_k_decay":1.0,
        "lr_noise":null,
        "lr_noise_pct":0.67,
        "lr_noise_std":1.0,
        "mean":[
            0.5,
            0.5,
            0.5
        ],
        "min_lr":1e-06,
        "mixup":0.8,
        "mixup_mode":"batch",
        "mixup_prob":1.0,
        "mixup_switch_prob":0.5,
        "model":"canvas_van_tiny",
        "momentum":0.9,
        "native_amp":false,
        "no_aug":false,
        "no_ddp_bb":false,
        "num_classes":1000,
        "num_workers":8,
        "opt":"adamw",
        "opt_betas":null,
        "opt_eps":null,
        "output":"",
        "patience_epochs":10,
        "pin_memory":true,
        "rank":0,
        "ratio":[
            0.75,
            1.3333333333333333
        ],
        "re_count":1,
        "re_mode":"pixel",
        "re_prob":0.25,
        "re_split":false,
        "resume":"",
        "root":"/data/zhaocg/ImageNet",
        "scale":[
            0.08,
            1.0
        ],
        "sched":"cosine",
        "seed":42,
        "smoothing":0.1,
        "std":[
            0.5,
            0.5,
            0.5
        ],
        "timestamp":1658419732836618843,
        "train_interpolation":"random",
        "train_split":"train",
        "tta":0,
        "use_multi_epochs_loader":false,
        "val_split":"validation",
        "vflip":0.0,
        "warmup_epochs":0,
        "warmup_lr":1e-06,
        "weight_decay":0.05,
        "world_size":1
    },
    "eval_metrics":[
        {
            "kernel_scales":[
                0.12717494926452635,
                0.11959270833015442,
                0.23198732672691344,
                0.23347837100028992,
                0.42890554934501635,
                0.35142784907341,
                0.22335944211006156,
                0.7756330954933166,
                0.33642734208106995,
                0.46687522834777834,
                0.7298001903915409,
                NaN,
                NaN
            ],
            "loss":NaN,
            "top1":20.684,
            "top5":42.728
        },
        {
            "kernel_scales":[
                0.40543116207122804,
                0.13036489377021782,
                0.23883738919258118,
                0.35596423719406123,
                0.42326777104377744,
                0.2315691505241394,
                0.30114673781394957,
                0.5425460341835024,
                0.39395365179061875,
                0.6712856631660468,
                NaN,
                NaN,
                NaN
            ],
            "loss":NaN,
            "top1":32.192,
            "top5":58.002
        },
        {
            "kernel_scales":[
                0.16671563395977013,
                0.11728998459815981,
                0.12825902452468868,
                0.2890946916389463,
                0.38705131120681785,
                0.2350392085838318,
                0.3337258174324034,
                0.366758949480057,
                0.44483147855758665,
                0.7534464710235599,
                0.4256520887374878,
                0.548384171056748,
                0.707406228599548
            ],
            "loss":2.946393942565918,
            "top1":40.006,
            "top5":66.262
        },
        {
            "kernel_scales":[
                0.23981469724655152,
                0.10797041991710662,
                0.15490454525470737,
                0.26170362174034123,
                0.37235184698104873,
                0.20494716639518737,
                0.3790479789924622,
                0.2981819117450716,
                0.407426364583969,
                0.7782634098243714,
                0.35521225804328943,
                0.49485160539627077,
                0.6899677377700808
            ],
            "loss":2.577742248840332,
            "top1":46.104,
            "top5":71.754
        },
        {
            "kernel_scales":[
                0.18131900142192842,
                0.09430350668430332,
                0.14707305846214302,
                0.30121389422416717,
                0.2821339071178438,
                0.20686865270137794,
                0.3830982081031799,
                0.2671658930683135,
                0.41084956739425676,
                0.719265626335144,
                0.31042430606842064,
                0.45042795485496523,
                0.614440119533539
            ],
            "loss":2.454272936706543,
            "top1":50.566,
            "top5":75.308
        }
    ],
    "extra":{
        "g_macs":2.218431336,
        "m_params":11.423
    },
    "timestamp":0,
    "train_metrics":[
        {
            "loss":6.241244795987246
        },
        {
            "loss":5.619652553780927
        },
        {
            "loss":5.304063614389734
        },
        {
            "loss":5.065148238857519
        },
        {
            "loss":4.882379270860015
        }
    ]
}